humpday/__init__.py
humpday/comparison/__init__.py
humpday/comparison/benchmarks.py
humpday/comparison/broken.py
humpday/comparison/eloformulas.py
humpday/comparison/eloratings.py
humpday/comparison/eloretrieval.py
humpday/comparison/limitations.py
humpday/comparison/naming.py
humpday/comparison/odious.py
humpday/comparison/suggestions.py
humpday/comparison/timing.py
humpday/comparison/timingretrieval.py
humpday/inclusion/__init__.py
humpday/inclusion/axplatforminclusion.py
humpday/inclusion/bayesoptinclusion.py
humpday/inclusion/dlibinclusion.py
humpday/inclusion/freelunchinclusion.py
humpday/inclusion/heboinclusion.py
humpday/inclusion/hyperoptinclusion.py
humpday/inclusion/nevergradinclusion.py
humpday/inclusion/nloptinclusion.py
humpday/inclusion/pybobyqainclusion.py
humpday/inclusion/winninginclusion.py
humpday/objectives/__init__.py
humpday/objectives/allobjectives.py
humpday/objectives/chatgptobjectives.py
humpday/objectives/classic.py
humpday/objectives/deapobjectives.py
humpday/objectives/horse.py
humpday/objectives/planar_h1.py
humpday/objectives/planar_h1_optimizer.py
humpday/objectives/portfolio.py
humpday/objectives/transforms.py
humpday/optimizers/__init__.py
humpday/optimizers/alloptimizers.py
humpday/optimizers/alltopoptimizers.py
humpday/optimizers/axcube.py
humpday/optimizers/bayesoptcube.py
humpday/optimizers/bobyqacube.py
humpday/optimizers/dlibcube.py
humpday/optimizers/freelunchcube.py
humpday/optimizers/hebocube.py
humpday/optimizers/hyperoptcube.py
humpday/optimizers/meta.py
humpday/optimizers/nevergradcube.py
humpday/optimizers/nloptcube.py
humpday/optimizers/optunacube.py
humpday/optimizers/platypuscube.py
humpday/optimizers/pymoocube.py
humpday/optimizers/pysotcube.py
humpday/optimizers/scipycube.py
humpday/optimizers/shgocube.py
humpday/optimizers/skoptcube.py
humpday/optimizers/swarmlibcube.py
humpday/optimizers/ultraoptcube.py
humpday/transforms/__init__.py
humpday/transforms/cubetosimplex.py
humpday/transforms/normhelper.py
humpday-0.7.1.dist-info/LICENSE
humpday-0.7.1.dist-info/METADATA
humpday-0.7.1.dist-info/WHEEL
humpday-0.7.1.dist-info/entry_points.txt
humpday-0.7.1.dist-info/top_level.txt
humpday-0.7.1.dist-info/RECORD
