Metadata-Version: 2.1
Name: humpday
Version: 0.7.1
Summary: Taking the pain out of choosing a Python global optimizer
Home-page: https://github.com/microprediction/humpday
Author: microprediction
Author-email: pcotton@intechinvestments.com
License: MIT
Classifier: License :: OSI Approved :: MIT License
Classifier: Programming Language :: Python :: 3
Classifier: Programming Language :: Python :: 3.7
License-File: LICENSE
Requires-Dist: wheel
Requires-Dist: numpy (>=1.21.5)
Requires-Dist: importlib-metadata (>=1.7.0)
Requires-Dist: getjson
Requires-Dist: scipy
Requires-Dist: funcy
Requires-Dist: winning (>=0.4.6)
Requires-Dist: microconventions (>=0.5.0)
Requires-Dist: landscapes
Requires-Dist: pymorton
Requires-Dist: scikit-learn
Provides-Extra: full
Requires-Dist: bayesian-optimization (>=1.2.0) ; extra == 'full'
Requires-Dist: optuna ; extra == 'full'
Requires-Dist: platypus-opt ; extra == 'full'
Requires-Dist: poap ; extra == 'full'
Requires-Dist: pysot ; extra == 'full'
Requires-Dist: ultraopt ; extra == 'full'
Requires-Dist: dlib ; extra == 'full'
Requires-Dist: ax-platform ; extra == 'full'
Requires-Dist: py-bobyqa ; extra == 'full'
Requires-Dist: hebo ; extra == 'full'
Requires-Dist: nlopt ; extra == 'full'
Requires-Dist: freelunch ; extra == 'full'
